AUTHORS
LICENSE
MANIFEST.in
VERSION
requirements.txt
setup.py
django_jinja/VERSION
django_jinja/__init__.py
django_jinja/middleware.py
django_jinja/response.py
django_jinja_middleware.egg-info/PKG-INFO
django_jinja_middleware.egg-info/SOURCES.txt
django_jinja_middleware.egg-info/dependency_links.txt
django_jinja_middleware.egg-info/requires.txt
django_jinja_middleware.egg-info/top_level.txt