Metadata-Version: 1.1
Name: django-jinja-middleware
Version: 2.0.1
Summary: Django middleware class that takes TemplateResponses and renders them with Jinja, instead of the Django stock templating language. For Python 2 or Python 3, and Django >= 1.4
Home-page: https://github.com/lukesneeringer/django-jinja/
Author: Luke Sneeringer
Author-email: luke@sneeringer.com
License: New BSD
Keywords: django,jinja,middleware
Platform: UNKNOWN
Classifier: Development Status :: 5 - Production/Stable
Classifier: Environment :: Web Environment
Classifier: Framework :: Django
Classifier: Intended Audience :: Developers
Classifier: License :: OSI Approved :: BSD License
Classifier: Operating System :: OS Independent
Classifier: Programming Language :: Python
Classifier: Programming Language :: Python :: 2.6
Classifier: Programming Language :: Python :: 2.7
Classifier: Programming Language :: Python :: 3.3
Classifier: Topic :: Software Development
Provides: django_jinja
